{
  "type": "FeatureCollection",
  "features": [
    {
      "stac_version": "$${env('stac_version', '1.0.0-rc2')}",
      "stac_extensions": [
        // skip SAR sensors
        "$filter{eop:parentIdentifier LIKE 'SENTINEL%' or eop:parentIdentifier LIKE 'LANDSAT%'},eo", 
        "view"
      ],
      "id": "${eop:identifier}",
      "type": "Feature",
      "geometry": "${footprint}",
      "bbox": [
        "$${minx(footprint)}",
        "$${miny(footprint)}",
        "$${maxx(footprint)}",
        "$${maxy(footprint)}"
      ],
      "properties": {
        "start_datetime": "$filter{timeStart is not null and timeEnd is not null and timeStart <> timeEnd},${timeStart}",
        "end_datetime": "$filter{timeStart is not null and timeEnd is not null and timeStart <> timeEnd},${timeEnd}",
        "datetime": "$filter{timeStart is not null and (timeEnd is null or timeStart = timeEnd)},${timeStart}",
        "created": "${eop:creationDate}",
        "updated": "${eop:modificationDate}",
        "platform": "${eop:productPlatform}",
        "instruments": [
          "$filter{eop:parentIdentifier = 'SENTINEL2'},msi",
          "$filter{eop:parentIdentifier = 'LANDSAT8'},oli",
          "$filter{eop:parentIdentifier = 'LANDSAT8'},tirs"
        ],
        "constellation": "$${strToLowerCase(eop:parentIdentifier)}",
        "eo:cloud_cover": "${opt:cloudCover}",
        // "view:off_nadir": "${opt:instrumentElevationAngle}",
        // "view:incidence_angle": "${opt:incidenceAngle}",
        // "view:azimuth": "${opt:instrumentAzimuthAngle}",
        "view:sun_azimuth": "${eop:illuminationAzimuthAngle}",
        "view:sun_elevation": "${eop:illuminationElevationAngle}",
        "sar:instrument_mode": "$filter{eop:parentIdentifier = 'SENTINEL1'},WV",
        "sar:frequency_band": "$filter{eop:parentIdentifier = 'SENTINEL1'},C",
        "sar:center_frequency": "${sar:dopplerFrequency}",
        "sar:center_frequency": "${sar:dopplerFrequency}",
        "sar:polarizations": "${sar:polarisationChannels}", // should be an array, what to do here?
        "sar:product_type": "$filter{eop:parentIdentifier = 'SENTINEL1'},GRD",
        "sar:observation_direction" : "$${strToLowerCase(sar:antennaLookDirection)}",
        "sat:orbit_state": "$${strToLowerCase(eop:orbitDirection)}",
        "sat:absolute_orbit": "${eop:orbitNumber}",
        "sat:anx_datetime": "${eop:startTimeFromAscendingNode}" // eoCompletionTimeFromAscendingNode?
      },
      "collection": "${eop:parentIdentifier}",
      "assets": {
        
      },
      "links": [
        {
          "href": "$${serviceLink('ogcapi/stac/collections/%s', eop:parentIdentifier)}",
          "rel": "collection",
          "type": "application/json"
        },
        {
          "href": "$${serviceLink('ogcapi/stac')}",
          "rel": "root",
          "type": "application/json"
        },
        {
          "href": "$${serviceLink('ogcapi/stac/collections/%s/items/%s', eop:parentIdentifier, eop:identifier)}",
          "rel": "self",
          "type": "application/geo+json"
        }
      ]
    }
  ]
}